<?xml version="1.0" encoding="utf-8" ?>
<dwsync>
<file name="bg_footer.png" server="ftp.inbeauty.com.tw//httpdocs/demo/" local="130691677916915604" remote="130691694600000000" Dst="0" />
<file name="bg_h1.png" server="ftp.inbeauty.com.tw//httpdocs/demo/" local="130691688080786944" remote="130691694600000000" Dst="0" />
<file name="bg_header.png" server="ftp.inbeauty.com.tw//httpdocs/demo/" local="130691677894984350" remote="130691694600000000" Dst="0" />
<file name="favicon.ico" server="ftp.inbeauty.com.tw//httpdocs/demo/" local="130691660832538434" remote="130691694600000000" Dst="0" />
<file name="grey.gif" server="ftp.inbeauty.com.tw//httpdocs/demo/" local="129365646359999999" remote="130691694600000000" Dst="0" />
<file name="bg_fotlogo.png" server="ftp.inbeauty.com.tw//httpdocs/demo/" local="130692418326558137" remote="130693273800000000" Dst="0" />
<file name="blank.gif" server="ftp.inbeauty.com.tw//httpdocs/demo/" local="130156207480000000" remote="130693273800000000" Dst="0" />
<file name="bg_nav.png" server="ftp.inbeauty.com.tw//httpdocs/demo/" local="130692216363407200" remote="130693273800000000" Dst="0" />
<file name="bg_navh2.png" server="ftp.inbeauty.com.tw//httpdocs/demo/" local="130692225483338830" remote="130693273800000000" Dst="0" />
<file name="captcha_image.jpg" server="ftp.inbeauty.com.tw//httpdocs/demo/" local="130168744873767583" remote="130693273800000000" Dst="0" />
<file name="fancybox_loading@2x.gif" server="ftp.inbeauty.com.tw//httpdocs/demo/" local="130156207480000000" remote="130693273800000000" Dst="0" />
<file name="fancybox_loading.gif" server="ftp.inbeauty.com.tw//httpdocs/demo/" local="130156207480000000" remote="130693273800000000" Dst="0" />
<file name="fancybox_overlay.png" server="ftp.inbeauty.com.tw//httpdocs/demo/" local="130156207480000000" remote="130693273800000000" Dst="0" />
<file name="fancybox_sprite@2x.png" server="ftp.inbeauty.com.tw//httpdocs/demo/" local="130156207480000000" remote="130693273800000000" Dst="0" />
<file name="fancybox_sprite.png" server="ftp.inbeauty.com.tw//httpdocs/demo/" local="130156207480000000" remote="130693273800000000" Dst="0" />
<file name="icon_link.png" server="ftp.inbeauty.com.tw//httpdocs/demo/" local="130692195632711472" remote="130693273800000000" Dst="0" />
<file name="my_qrcode.jpg" server="ftp.inbeauty.com.tw//httpdocs/demo/" local="130589797234643198" remote="130693273800000000" Dst="0" />
<file name="banner_02.jpg" server="ftp.inbeauty.com.tw//httpdocs/demo/" local="130693306088879716" remote="130693340400000000" Dst="0" />
<file name="banner_01.jpg" server="ftp.inbeauty.com.tw//httpdocs/demo/" local="130693306088939719" remote="130693340400000000" Dst="0" />
<file name="banner_03.jpg" server="ftp.inbeauty.com.tw//httpdocs/demo/" local="130693306088909718" remote="130693340400000000" Dst="0" />
<file name="pic_ad-01.jpg" server="ftp.inbeauty.com.tw//httpdocs/demo/" local="130694290912598502" remote="130694715600000000" Dst="0" />
<file name="pic_ad-02.jpg" server="ftp.inbeauty.com.tw//httpdocs/demo/" local="130694290912628504" remote="130694715600000000" Dst="0" />
<file name="title_hot-service.png" server="ftp.inbeauty.com.tw//httpdocs/demo/" local="130694268356808385" remote="130694715600000000" Dst="0" />
<file name="pic_ad-03.jpg" server="ftp.inbeauty.com.tw//httpdocs/demo/" local="130694290912618504" remote="130694715600000000" Dst="0" />
<file name="pic_ad-04.jpg" server="ftp.inbeauty.com.tw//httpdocs/demo/" local="130694290912598502" remote="130694715600000000" Dst="0" />
</dwsync>